passgen_llm/__init__.py
passgen_llm/main.py
passgen_llm/prompts.py
passgen_llm-2025.12.21181318.dist-info/METADATA
passgen_llm-2025.12.21181318.dist-info/WHEEL
passgen_llm-2025.12.21181318.dist-info/top_level.txt
passgen_llm-2025.12.21181318.dist-info/RECORD
