Metadata-Version: 2.4
Name: passgen-llm
Version: 2025.12.21181318
Summary: A new package that takes user-provided text input (such as event details, membership information, or coupon data) and uses an LLM to generate structured, formatted pass content for Apple Wallet. It en
Author-email: passgen-llm <hi@eugene.plus>
License: MIT
Project-URL: Homepage, https://github.com/chigwell/passgen-llm
Requires-Python: >=3.9
Requires-Dist: langchain-llm7>=0.0.0
Requires-Dist: llmatch-messages>=0.0.0
Requires-Dist: langchain-core>=0.3.0
